cli.py
mtbtk/__init__.py
mtbtk/data/GO.json
mtbtk/data/KEGG_pathways.json
mtbtk/data/TF_genes.json
mtbtk/data/domains.json
mtbtk/data/epitopes.json
mtbtk/data/genes.json
mtbtk/data/lineage_info.json
mtbtk/tbgea/__init__.py
mtbtk/tbgea/config.py
mtbtk/tbgea/enrichment_analyzer.py
mtbtk/tbva/SNP_effect_annotator.py
mtbtk/tbva/__init__.py
mtbtk/tbva/annotator.py
mtbtk/tbva/config.py
mtbtk/tbva/lineage_identifier.py
mtbtk/tbva/vcf_parser.py
MtbTk-0.0.2.dist-info/LICENSE
MtbTk-0.0.2.dist-info/METADATA
MtbTk-0.0.2.dist-info/WHEEL
MtbTk-0.0.2.dist-info/top_level.txt
MtbTk-0.0.2.dist-info/RECORD
